jaxion/__init__.py
jaxion/analysis.py
jaxion/constants.py
jaxion/cosmology.py
jaxion/defaults.json
jaxion/gravity.py
jaxion/hydro.py
jaxion/particles.py
jaxion/quantum.py
jaxion/simulation.py
jaxion/utils.py
jaxion/visualization.py
jaxion-0.0.7.dist-info/licenses/LICENSE
jaxion-0.0.7.dist-info/METADATA
jaxion-0.0.7.dist-info/WHEEL
jaxion-0.0.7.dist-info/top_level.txt
jaxion-0.0.7.dist-info/RECORD
