Metadata-Version: 2.4
Name: jaxion
Version: 0.0.7
Summary: A differentiable simulation library for fuzzy dark matter in JAX
Author-email: Philip Mocz <philip.mocz@gmail.com>
License-Expression: Apache-2.0
Project-URL: Documentation, https://jaxion.readthedocs.io
Project-URL: Homepage, https://github.com/JaxionProject/jaxion
Requires-Python: >=3.11
License-File: LICENSE
Requires-Dist: jax==0.5.3
Requires-Dist: jaxdecomp==0.2.7
Requires-Dist: tensorflow
Requires-Dist: orbax-checkpoint==0.11.18
Requires-Dist: optax==0.2.5
Requires-Dist: numpy
Requires-Dist: matplotlib
Requires-Dist: setuptools>=70.1.1
Provides-Extra: cuda12
Requires-Dist: jax[cuda12]==0.5.3; extra == "cuda12"
Dynamic: license-file
